MANIFEST.in
README.md
setup.py
django_plantains.egg-info/PKG-INFO
django_plantains.egg-info/SOURCES.txt
django_plantains.egg-info/dependency_links.txt
django_plantains.egg-info/not-zip-safe
django_plantains.egg-info/requires.txt
django_plantains.egg-info/top_level.txt
plantains/__init__.py
plantains/models.py
plantains/urls.py
plantains/views.py
plantains/migrations/0001_initial.py
plantains/migrations/__init__.py