Metadata-Version: 1.1
Name: django-plantains
Version: 0.1.1
Summary: Persistable oauth2 Mailchimp backend for Django.
Home-page: https://github.com/avelis/django-plantains/
Author: Andrew Velis
Author-email: andrew.velis@gmail.com
License: BSD
Keywords: django,mailchimp,oauth2
Platform: UNKNOWN
Classifier: Development Status :: 4 - Beta
Classifier: Environment :: Web Environment
Classifier: Intended Audience :: Developers
Classifier: License :: OSI Approved :: BSD License
Classifier: Operating System :: OS Independent
Classifier: Programming Language :: Python
Classifier: Programming Language :: Python :: 2.7
Classifier: Framework :: Django
Classifier: Topic :: Software Development :: Libraries :: Python Modules
